Workbook

Sheet Lisez-moi
A1: Tunexa - Backlog des tickets pour validation client
A3: Objet | B3: Liste exhaustive des tâches (tickets) nécessaires pour construire la marketplace Tunexa, à valider par le client avant import dans l'outil de gestion (Jira, Trello, Linear...).
A4: Document de référence | B4: docs/FONCTIONNALITES.md (cahier des fonctionnalités)
A6: Onglets
A7: Tickets | B7: Un ticket par ligne : identifiant, épique, titre, description, critères d'acceptation, type, priorité, phase, estimation, dépendances.
A8: Synthèse | B8: Totaux calculés automatiquement par épique, priorité, phase et décision client (formules, se mettent à jour seules).
A10: À remplir par le client
A11: Colonnes jaunes | B11: « Décision client » (liste déroulante) et « Commentaire client » dans l'onglet Tickets. Ne pas modifier les autres colonnes.
A12: Exemple | B12: AUTH-01 → Décision : « À modifier » ; Commentaire : « Ajouter aussi la vérification par WhatsApp ».
A14: Valeurs de « Décision client »
A15: À valider | B15: Pas encore revu (valeur par défaut).
A16: Validé | B16: Le ticket est accepté tel quel.
A17: À modifier | B17: Accepté sous réserve des changements indiqués en commentaire.
A18: Refusé | B18: Le ticket est retiré du projet.
A19: Reporté | B19: Accepté mais déplacé à une phase ultérieure.
A21: Priorités
A22: P0 - Phase 1 - MVP | B22: Indispensable au lancement.
A23: P1 - Phase 2 - Croissance | B23: Peu après le lancement.
A24: P2 - Phase 3 - Expansion | B24: Évolutions futures.
A26: Estimation | B26: En jours-homme (j/h), effort de développement indicatif hors gestion de projet. Hypothèse de l'équipe technique, à affiner lors du découpage en sprints.
A27: Hypothèses | B27: Les prestataires (passerelle de paiement, transporteurs, fournisseur SMS) restent à choisir par le client. Les documents légaux, la déclaration INPDP et la validation fiscale des factures relèvent du client et de ses conseils (juriste, expert-comptable).

Sheet Synthèse
A1: Synthèse du backlog Tunexa
A2: Tous les chiffres sont des formules liées à l'onglet Tickets.
A4: Épique | B4: Nb tickets | C4: Total (j/h) | D4: P0 (j/h) | E4: P1 (j/h) | F4: P2 (j/h) | G4: Validés | H4: À modifier | I4: Refusés | J4: % validés
A5: SETUP - Socle technique & infrastructure | B5: =COUNTIF(Tickets!$B$2:$B$159,$A5) -> 7 | C5: =SUMIF(Tickets!$B$2:$B$159,$A5,Tickets!$I$2:$I$159) -> 34 | D5: =SUMIFS(Tickets!$I$2:$I$159,Tickets!$B$2:$B$159,$A5,Tickets!$G$2:$G$159,"P0") -> 34 | E5: =SUMIFS(Tickets!$I$2:$I$159,Tickets!$B$2:$B$159,$A5,Tickets!$G$2:$G$159,"P1") -> 0 | F5: =SUMIFS(Tickets!$I$2:$I$159,Tickets!$B$2:$B$159,$A5,Tickets!$G$2:$G$159,"P2") -> 0 | G5: =COUNTIFS(Tickets!$B$2:$B$159,$A5,Tickets!$K$2:$K$159,"Validé") -> 0 | H5: =COUNTIFS(Tickets!$B$2:$B$159,$A5,Tickets!$K$2:$K$159,"À modifier") -> 0 | I5: =COUNTIFS(Tickets!$B$2:$B$159,$A5,Tickets!$K$2:$K$159,"Refusé") -> 0 | J5: =IF(B5=0,0,G5/B5) -> 0
A6: AUTH - Comptes & authentification | B6: =COUNTIF(Tickets!$B$2:$B$159,$A6) -> 11 | C6: =SUMIF(Tickets!$B$2:$B$159,$A6,Tickets!$I$2:$I$159) -> 32 | D6: =SUMIFS(Tickets!$I$2:$I$159,Tickets!$B$2:$B$159,$A6,Tickets!$G$2:$G$159,"P0") -> 24 | E6: =SUMIFS(Tickets!$I$2:$I$159,Tickets!$B$2:$B$159,$A6,Tickets!$G$2:$G$159,"P1") -> 8 | F6: =SUMIFS(Tickets!$I$2:$I$159,Tickets!$B$2:$B$159,$A6,Tickets!$G$2:$G$159,"P2") -> 0 | G6: =COUNTIFS(Tickets!$B$2:$B$159,$A6,Tickets!$K$2:$K$159,"Validé") -> 0 | H6: =COUNTIFS(Tickets!$B$2:$B$159,$A6,Tickets!$K$2:$K$159,"À modifier") -> 0 | I6: =COUNTIFS(Tickets!$B$2:$B$159,$A6,Tickets!$K$2:$K$159,"Refusé") -> 0 | J6: =IF(B6=0,0,G6/B6) -> 0
A7: CAT - Catalogue & recherche | B7: =COUNTIF(Tickets!$B$2:$B$159,$A7) -> 13 | C7: =SUMIF(Tickets!$B$2:$B$159,$A7,Tickets!$I$2:$I$159) -> 57 | D7: =SUMIFS(Tickets!$I$2:$I$159,Tickets!$B$2:$B$159,$A7,Tickets!$G$2:$G$159,"P0") -> 38 | E7: =SUMIFS(Tickets!$I$2:$I$159,Tickets!$B$2:$B$159,$A7,Tickets!$G$2:$G$159,"P1") -> 9 | F7: =SUMIFS(Tickets!$I$2:$I$159,Tickets!$B$2:$B$159,$A7,Tickets!$G$2:$G$159,"P2") -> 10 | G7: =COUNTIFS(Tickets!$B$2:$B$159,$A7,Tickets!$K$2:$K$159,"Validé") -> 0 | H7: =COUNTIFS(Tickets!$B$2:$B$159,$A7,Tickets!$K$2:$K$159,"À modifier") -> 0 | I7: =COUNTIFS(Tickets!$B$2:$B$159,$A7,Tickets!$K$2:$K$159,"Refusé") -> 0 | J7: =IF(B7=0,0,G7/B7) -> 0
A8: PDP - Fiche produit | B8: =COUNTIF(Tickets!$B$2:$B$159,$A8) -> 7 | C8: =SUMIF(Tickets!$B$2:$B$159,$A8,Tickets!$I$2:$I$159) -> 21 | D8: =SUMIFS(Tickets!$I$2:$I$159,Tickets!$B$2:$B$159,$A8,Tickets!$G$2:$G$159,"P0") -> 19 | E8: =SUMIFS(Tickets!$I$2:$I$159,Tickets!$B$2:$B$159,$A8,Tickets!$G$2:$G$159,"P1") -> 2 | F8: =SUMIFS(Tickets!$I$2:$I$159,Tickets!$B$2:$B$159,$A8,Tickets!$G$2:$G$159,"P2") -> 0 | G8: =COUNTIFS(Tickets!$B$2:$B$159,$A8,Tickets!$K$2:$K$159,"Validé") -> 0 | H8: =COUNTIFS(Tickets!$B$2:$B$159,$A8,Tickets!$K$2:$K$159,"À modifier") -> 0 | I8: =COUNTIFS(Tickets!$B$2:$B$159,$A8,Tickets!$K$2:$K$159,"Refusé") -> 0 | J8: =IF(B8=0,0,G8/B8) -> 0
A9: CART - Panier & checkout | B9: =COUNTIF(Tickets!$B$2:$B$159,$A9) -> 8 | C9: =SUMIF(Tickets!$B$2:$B$159,$A9,Tickets!$I$2:$I$159) -> 22 | D9: =SUMIFS(Tickets!$I$2:$I$159,Tickets!$B$2:$B$159,$A9,Tickets!$G$2:$G$159,"P0") -> 20 | E9: =SUMIFS(Tickets!$I$2:$I$159,Tickets!$B$2:$B$159,$A9,Tickets!$G$2:$G$159,"P1") -> 2 | F9: =SUMIFS(Tickets!$I$2:$I$159,Tickets!$B$2:$B$159,$A9,Tickets!$G$2:$G$159,"P2") -> 0 | G9: =COUNTIFS(Tickets!$B$2:$B$159,$A9,Tickets!$K$2:$K$159,"Validé") -> 0 | H9: =COUNTIFS(Tickets!$B$2:$B$159,$A9,Tickets!$K$2:$K$159,"À modifier") -> 0 | I9: =COUNTIFS(Tickets!$B$2:$B$159,$A9,Tickets!$K$2:$K$159,"Refusé") -> 0 | J9: =IF(B9=0,0,G9/B9) -> 0
A10: PAY - Paiement | B10: =COUNTIF(Tickets!$B$2:$B$159,$A10) -> 10 | C10: =SUMIF(Tickets!$B$2:$B$159,$A10,Tickets!$I$2:$I$159) -> 44 | D10: =SUMIFS(Tickets!$I$2:$I$159,Tickets!$B$2:$B$159,$A10,Tickets!$G$2:$G$159,"P0") -> 15 | E10: =SUMIFS(Tickets!$I$2:$I$159,Tickets!$B$2:$B$159,$A10,Tickets!$G$2:$G$159,"P1") -> 16 | F10: =SUMIFS(Tickets!$I$2:$I$159,Tickets!$B$2:$B$159,$A10,Tickets!$G$2:$G$159,"P2") -> 13 | G10: =COUNTIFS(Tickets!$B$2:$B$159,$A10,Tickets!$K$2:$K$159,"Validé") -> 0 | H10: =COUNTIFS(Tickets!$B$2:$B$159,$A10,Tickets!$K$2:$K$159,"À modifier") -> 0 | I10: =COUNTIFS(Tickets!$B$2:$B$159,$A10,Tickets!$K$2:$K$159,"Refusé") -> 0 | J10: =IF(B10=0,0,G10/B10) -> 0
A11: SHIP - Livraison & logistique | B11: =COUNTIF(Tickets!$B$2:$B$159,$A11) -> 10 | C11: =SUMIF(Tickets!$B$2:$B$159,$A11,Tickets!$I$2:$I$159) -> 56 | D11: =SUMIFS(Tickets!$I$2:$I$159,Tickets!$B$2:$B$159,$A11,Tickets!$G$2:$G$159,"P0") -> 24 | E11: =SUMIFS(Tickets!$I$2:$I$159,Tickets!$B$2:$B$159,$A11,Tickets!$G$2:$G$159,"P1") -> 12 | F11: =SUMIFS(Tickets!$I$2:$I$159,Tickets!$B$2:$B$159,$A11,Tickets!$G$2:$G$159,"P2") -> 20 | G11: =COUNTIFS(Tickets!$B$2:$B$159,$A11,Tickets!$K$2:$K$159,"Validé") -> 0 | H11: =COUNTIFS(Tickets!$B$2:$B$159,$A11,Tickets!$K$2:$K$159,"À modifier") -> 0 | I11: =COUNTIFS(Tickets!$B$2:$B$159,$A11,Tickets!$K$2:$K$159,"Refusé") -> 0 | J11: =IF(B11=0,0,G11/B11) -> 0
A12: ORD - Commandes & retours | B12: =COUNTIF(Tickets!$B$2:$B$159,$A12) -> 7 | C12: =SUMIF(Tickets!$B$2:$B$159,$A12,Tickets!$I$2:$I$159) -> 23 | D12: =SUMIFS(Tickets!$I$2:$I$159,Tickets!$B$2:$B$159,$A12,Tickets!$G$2:$G$159,"P0") -> 19 | E12: =SUMIFS(Tickets!$I$2:$I$159,Tickets!$B$2:$B$159,$A12,Tickets!$G$2:$G$159,"P1") -> 4 | F12: =SUMIFS(Tickets!$I$2:$I$159,Tickets!$B$2:$B$159,$A12,Tickets!$G$2:$G$159,"P2") -> 0 | G12: =COUNTIFS(Tickets!$B$2:$B$159,$A12,Tickets!$K$2:$K$159,"Validé") -> 0 | H12: =COUNTIFS(Tickets!$B$2:$B$159,$A12,Tickets!$K$2:$K$159,"À modifier") -> 0 | I12: =COUNTIFS(Tickets!$B$2:$B$159,$A12,Tickets!$K$2:$K$159,"Refusé") -> 0 | J12: =IF(B12=0,0,G12/B12) -> 0
A13: SELL - Espace vendeur (Seller Center) | B13: =COUNTIF(Tickets!$B$2:$B$159,$A13) -> 14 | C13: =SUMIF(Tickets!$B$2:$B$159,$A13,Tickets!$I$2:$I$159) -> 65 | D13: =SUMIFS(Tickets!$I$2:$I$159,Tickets!$B$2:$B$159,$A13,Tickets!$G$2:$G$159,"P0") -> 36 | E13: =SUMIFS(Tickets!$I$2:$I$159,Tickets!$B$2:$B$159,$A13,Tickets!$G$2:$G$159,"P1") -> 29 | F13: =SUMIFS(Tickets!$I$2:$I$159,Tickets!$B$2:$B$159,$A13,Tickets!$G$2:$G$159,"P2") -> 0 | G13: =COUNTIFS(Tickets!$B$2:$B$159,$A13,Tickets!$K$2:$K$159,"Validé") -> 0 | H13: =COUNTIFS(Tickets!$B$2:$B$159,$A13,Tickets!$K$2:$K$159,"À modifier") -> 0 | I13: =COUNTIFS(Tickets!$B$2:$B$159,$A13,Tickets!$K$2:$K$159,"Refusé") -> 0 | J13: =IF(B13=0,0,G13/B13) -> 0
A14: REV - Avis & questions / réponses | B14: =COUNTIF(Tickets!$B$2:$B$159,$A14) -> 6 | C14: =SUMIF(Tickets!$B$2:$B$159,$A14,Tickets!$I$2:$I$159) -> 15 | D14: =SUMIFS(Tickets!$I$2:$I$159,Tickets!$B$2:$B$159,$A14,Tickets!$G$2:$G$159,"P0") -> 6 | E14: =SUMIFS(Tickets!$I$2:$I$159,Tickets!$B$2:$B$159,$A14,Tickets!$G$2:$G$159,"P1") -> 9 | F14: =SUMIFS(Tickets!$I$2:$I$159,Tickets!$B$2:$B$159,$A14,Tickets!$G$2:$G$159,"P2") -> 0 | G14: =COUNTIFS(Tickets!$B$2:$B$159,$A14,Tickets!$K$2:$K$159,"Validé") -> 0 | H14: =COUNTIFS(Tickets!$B$2:$B$159,$A14,Tickets!$K$2:$K$159,"À modifier") -> 0 | I14: =COUNTIFS(Tickets!$B$2:$B$159,$A14,Tickets!$K$2:$K$159,"Refusé") -> 0 | J14: =IF(B14=0,0,G14/B14) -> 0
A15: MKT - Marketing & fidélisation | B15: =COUNTIF(Tickets!$B$2:$B$159,$A15) -> 12 | C15: =SUMIF(Tickets!$B$2:$B$159,$A15,Tickets!$I$2:$I$159) -> 47 | D15: =SUMIFS(Tickets!$I$2:$I$159,Tickets!$B$2:$B$159,$A15,Tickets!$G$2:$G$159,"P0") -> 6 | E15: =SUMIFS(Tickets!$I$2:$I$159,Tickets!$B$2:$B$159,$A15,Tickets!$G$2:$G$159,"P1") -> 27 | F15: =SUMIFS(Tickets!$I$2:$I$159,Tickets!$B$2:$B$159,$A15,Tickets!$G$2:$G$159,"P2") -> 14 | G15: =COUNTIFS(Tickets!$B$2:$B$159,$A15,Tickets!$K$2:$K$159,"Validé") -> 0 | H15: =COUNTIFS(Tickets!$B$2:$B$159,$A15,Tickets!$K$2:$K$159,"À modifier") -> 0 | I15: =COUNTIFS(Tickets!$B$2:$B$159,$A15,Tickets!$K$2:$K$159,"Refusé") -> 0 | J15: =IF(B15=0,0,G15/B15) -> 0
A16: NOTIF - Notifications | B16: =COUNTIF(Tickets!$B$2:$B$159,$A16) -> 5 | C16: =SUMIF(Tickets!$B$2:$B$159,$A16,Tickets!$I$2:$I$159) -> 16 | D16: =SUMIFS(Tickets!$I$2:$I$159,Tickets!$B$2:$B$159,$A16,Tickets!$G$2:$G$159,"P0") -> 10 | E16: =SUMIFS(Tickets!$I$2:$I$159,Tickets!$B$2:$B$159,$A16,Tickets!$G$2:$G$159,"P1") -> 6 | F16: =SUMIFS(Tickets!$I$2:$I$159,Tickets!$B$2:$B$159,$A16,Tickets!$G$2:$G$159,"P2") -> 0 | G16: =COUNTIFS(Tickets!$B$2:$B$159,$A16,Tickets!$K$2:$K$159,"Validé") -> 0 | H16: =COUNTIFS(Tickets!$B$2:$B$159,$A16,Tickets!$K$2:$K$159,"À modifier") -> 0 | I16: =COUNTIFS(Tickets!$B$2:$B$159,$A16,Tickets!$K$2:$K$159,"Refusé") -> 0 | J16: =IF(B16=0,0,G16/B16) -> 0
... A24: QA - Tests, recette & lancement | B24: =COUNTIF(Tickets!$B$2:$B$159,$A24) -> 5 | C24: =SUMIF(Tickets!$B$2:$B$159,$A24,Tickets!$I$2:$I$159) -> 28 | D24: =SUMIFS(Tickets!$I$2:$I$159,Tickets!$B$2:$B$159,$A24,Tickets!$G$2:$G$159,"P0") -> 28 | E24: =SUMIFS(Tickets!$I$2:$I$159,Tickets!$B$2:$B$159,$A24,Tickets!$G$2:$G$159,"P1") -> 0 | F24: =SUMIFS(Tickets!$I$2:$I$159,Tickets!$B$2:$B$159,$A24,Tickets!$G$2:$G$159,"P2") -> 0 | G24: =COUNTIFS(Tickets!$B$2:$B$159,$A24,Tickets!$K$2:$K$159,"Validé") -> 0 | H24: =COUNTIFS(Tickets!$B$2:$B$159,$A24,Tickets!$K$2:$K$159,"À modifier") -> 0 | I24: =COUNTIFS(Tickets!$B$2:$B$159,$A24,Tickets!$K$2:$K$159,"Refusé") -> 0 | J24: =IF(B24=0,0,G24/B24) -> 0
A25: TOTAL | B25: =SUM(B5:B24) -> 158 | C25: =SUM(C5:C24) -> 679 | D25: =SUM(D5:D24) -> 347 | E25: =SUM(E5:E24) -> 239 | F25: =SUM(F5:F24) -> 93 | G25: =SUM(G5:G24) -> 0 | H25: =SUM(H5:H24) -> 0 | I25: =SUM(I5:I24) -> 0 | J25: =IF(B25=0,0,G25/B25) -> 0
A28: Phase | B28: Nb tickets | C28: Total (j/h) | D28: Mois-homme (≈20 j/mois)
A29: Phase 1 - MVP | B29: =COUNTIF(Tickets!$H$2:$H$159,$A29) -> 94 | C29: =SUMIF(Tickets!$H$2:$H$159,$A29,Tickets!$I$2:$I$159) -> 347 | D29: =C29/$B$34 -> 17.35
A30: Phase 2 - Croissance | B30: =COUNTIF(Tickets!$H$2:$H$159,$A30) -> 53 | C30: =SUMIF(Tickets!$H$2:$H$159,$A30,Tickets!$I$2:$I$159) -> 239 | D30: =C30/$B$34 -> 11.95
A31: Phase 3 - Expansion | B31: =COUNTIF(Tickets!$H$2:$H$159,$A31) -> 11 | C31: =SUMIF(Tickets!$H$2:$H$159,$A31,Tickets!$I$2:$I$159) -> 93 | D31: =C31/$B$34 -> 4.65
A32: TOTAL | B32: =SUM(B29:B31) -> 158 | C32: =SUM(C29:C31) -> 679 | D32: =C32/$B$34 -> 33.95
A34: Jours ouvrés par mois (hypothèse) | B34: 20 | C34: Modifiable
A37: Décision client | B37: Nb tickets | C37: % du total
A38: À valider | B38: =COUNTIF(Tickets!$K$2:$K$159,$A38) -> 158 | C38: =IF($B$25=0,0,B38/$B$25) -> 1
A39: Validé | B39: =COUNTIF(Tickets!$K$2:$K$159,$A39) -> 0 | C39: =IF($B$25=0,0,B39/$B$25) -> 0
A40: À modifier | B40: =COUNTIF(Tickets!$K$2:$K$159,$A40) -> 0 | C40: =IF($B$25=0,0,B40/$B$25) -> 0
A41: Refusé | B41: =COUNTIF(Tickets!$K$2:$K$159,$A41) -> 0 | C41: =IF($B$25=0,0,B41/$B$25) -> 0
A42: Reporté | B42: =COUNTIF(Tickets!$K$2:$K$159,$A42) -> 0 | C42: =IF($B$25=0,0,B42/$B$25) -> 0

Sheet Tickets
A1: ID | B1: Épique | C1: Titre | D1: Description | E1: Critères d'acceptation | F1: Type | G1: Priorité | H1: Phase | I1: Estimation (j/h) | J1: Dépendances | K1: Décision client | L1: Commentaire client
A2: SETUP-01 | B2: SETUP - Socle technique & infrastructure | C2: Initialiser les dépôts et l'architecture du projet | D2: Créer le monorepo (web, API, back-office), conventions de code, linting, structure du monolithe modulaire. | E2: • Dépôt créé avec README • Lint et format automatiques • Structure des modules validée par le lead tech | F2: Tâche technique | G2: P0 | H2: Phase 1 - MVP | I2: 3 | J2: - | K2: À valider
A3: SETUP-02 | B3: SETUP - Socle technique & infrastructure | C3: Mettre en place la CI/CD | D3: Pipeline GitHub Actions : build, tests, analyse qualité, déploiement automatique sur staging et production. | E3: • Chaque push lance build + tests • Déploiement staging automatique sur la branche principale • Déploiement production sur validation manuelle | F3: Tâche technique | G3: P0 | H3: Phase 1 - MVP | I3: 4 | J3: SETUP-01 | K3: À valider
A4: SETUP-03 | B4: SETUP - Socle technique & infrastructure | C4: Provisionner les environnements (dev, staging, prod) | D4: Hébergement, base PostgreSQL, Redis, stockage objets pour les images, CDN, nom de domaine et certificats HTTPS. | E4: • 3 environnements isolés et accessibles • HTTPS actif • Sauvegardes quotidiennes de la base configurées | F4: Tâche technique | G4: P0 | H4: Phase 1 - MVP | I4: 5 | J4: SETUP-01 | K4: À valider
A5: SETUP-04 | B5: SETUP - Socle technique & infrastructure | C5: Mettre en place l'observabilité | D5: Logs centralisés, métriques, alertes, suivi des erreurs front et back. | E5: • Erreurs remontées dans un outil de suivi • Alerte si disponibilité < 99,9 % • Tableau de bord des métriques API | F5: Tâche technique | G5: P0 | H5: Phase 1 - MVP | I5: 3 | J5: SETUP-03 | K5: À valider
A6: SETUP-05 | B6: SETUP - Socle technique & infrastructure | C6: Internationalisation ar / fr / en avec RTL | D6: Socle i18n pour le web et le back-office : traductions, bascule de langue, mise en page de droite à gauche pour l'arabe. | E6: • Bascule de langue sans rechargement complet • Mise en page RTL correcte en arabe • Fichiers de traduction éditables | F6: Tâche technique | G6: P0 | H6: Phase 1 - MVP | I6: 4 | J6: SETUP-01 | K6: À valider
A7: SETUP-06 | B7: SETUP - Socle technique & infrastructure | C7: Format monétaire TND et référentiels tunisiens | D7: Affichage des prix en TND avec 3 décimales (millimes) ; import du référentiel gouvernorats / délégations / localités / codes postaux. | E7: • Prix affichés au format 1 249,900 DT • 24 gouvernorats et leurs délégations chargés • Référentiel modifiable dans le back-office | F7: Tâche technique | G7: P0 | H7: Phase 1 - MVP | I7: 3 | J7: SETUP-03 | K7: À valider
A8: SETUP-07 | B8: SETUP - Socle technique & infrastructure | C8: Design system et maquettes UI | D8: Charte graphique, composants réutilisables, maquettes des écrans clés (accueil, liste, fiche produit, panier, checkout, compte, espace vendeur). | E8: • Maquettes validées par le client • Bibliothèque de composants documentée • Version mobile et RTL incluses | F8: Design | G8: P0 | H8: Phase 1 - MVP | I8: 12 | J8: - | K8: À valider
A9: AUTH-01 | B9: AUTH - Comptes & authentification | C9: Inscription par téléphone + OTP SMS | D9: Le client s'inscrit avec son numéro (+216) et reçoit un code SMS de vérification. | E9: • Format +216 XX XXX XXX validé • Code OTP à 6 chiffres, valable 5 minutes • Maximum 3 renvois par heure | F9: Story | G9: P0 | H9: Phase 1 - MVP | I9: 4 | J9: AUTH-07 | K9: À valider
A10: AUTH-02 | B10: AUTH - Comptes & authentification | C10: Inscription et connexion par e-mail + mot de passe | D10: Alternative à l'inscription par téléphone, avec vérification de l'e-mail. | E10: • E-mail de confirmation envoyé • Mot de passe : 8 caractères minimum • Mot de passe stocké haché | F10: Story | G10: P0 | H10: Phase 1 - MVP | I10: 3 | J10: - | K10: À valider
A11: AUTH-03 | B11: AUTH - Comptes & authentification | C11: Mot de passe oublié | D11: Réinitialisation par SMS ou e-mail. | E11: • Lien / code valable 30 minutes • Ancien mot de passe invalidé après changement | F11: Story | G11: P0 | H11: Phase 1 - MVP | I11: 2 | J11: AUTH-02 | K11: À valider
A12: AUTH-04 | B12: AUTH - Comptes & authentification | C12: Gestion du profil client | D12: Modification nom, prénom, téléphone, e-mail, date de naissance, langue préférée. | E12: • Changement de téléphone revérifié par OTP • Modifications enregistrées et visibles immédiatement | F12: Story | G12: P0 | H12: Phase 1 - MVP | I12: 2 | J12: AUTH-01 | K12: À valider
A13: AUTH-05 | B13: AUTH - Comptes & authentification | C13: Carnet d'adresses | D13: Adresses multiples avec gouvernorat, délégation, localité, code postal, point de repère et adresse par défaut. | E13: • Listes déroulantes dépendantes gouvernorat → délégation → localité • Champ « point de repère » • Une adresse par défaut | F13: Story | G13: P0 | H13: Phase 1 - MVP | I13: 3 | J13: SETUP-06 | K13: À valider
... A159: QA-05 | B159: QA - Tests, recette & lancement | C159: Mise en production | D159: Bascule en production, surveillance renforcée, plan de retour arrière. | E159: • Checklist de mise en production complétée | F159: Tâche technique | G159: P0 | H159: Phase 1 - MVP | I159: 2 | J159: QA-03 | K159: À valider
